stage1_fetch/IF_ID_Register.v
module IF_ID_Register (
    input  wire clk,
    input  wire rst,
    input  wire stall, 
    input  wire flush,          
    input [31:0] if_PC,
    input [31:0] if_PC_plus_4,
    input [31:0] if_instruction,
    output reg [31:0] id_PC,
    output reg [31:0] id_PC_plus_4,
    output reg [31:0] id_instruction
);
    localparam NOP = 32'h0000_0013;
    always @ (posedge clk) begin 
        if (rst || flush) begin 
            id_instruction <= NOP; 
            id_PC          <= 'd0;          // Flushing PC
            id_PC_plus_4   <= 'd0;
        end
        else if (!stall) begin 
            id_instruction <= if_instruction;
            id_PC          <= if_PC;
            id_PC_plus_4   <= if_PC_plus_4;
        end
    end
endmodule

stage1_fetch/Instruction_Fetch.v
`timescale 1ns/1ps
module  Instruction_Fetch (
    input wire clk, 
    input wire rst,  
    input wire stall, 
    input wire branch_taken,
    input wire [31:0] branch_target,
    output reg [31:0] PC, 
    output wire [31:0] next_PC,
    output wire [31:0] PC_plus_4, 
    output wire [31:0] instruction
);
    reg [31:0] imem [0:63];
    assign PC_plus_4  =  PC + 32'd4;
    assign next_PC = branch_taken ? branch_target : PC_plus_4;  
    assign instruction = imem[PC[7:2]];
    always @ (posedge clk) begin 
        if (rst) begin 
            PC <= 'd0; 
        end  
        else if (!stall) begin 
            PC <= next_PC;
        end
    end
    initial begin
    imem[0] = 32'h00500093; // addi x1, x0, 5
    imem[1] = 32'h00a00113; // addi x2, x0, 10
    imem[2] = 32'h002081b3; // add  x3, x1, x2
    imem[3] = 32'h40208233; // sub  x4, x1, x2
    imem[4] = 32'h003102b3; // add  x5, x2, x3
    imem[5] = 32'h00000013; // nop
end
endmodule

stage1_fetch/fetch_tb.v
`timescale 1ns/1ps
`include "IF_ID_Register.v"
`include "Instruction_Fetch.v"

module tb_fetch () ;
    reg        clk;
    reg        rst;
    reg        stall;
    reg        flush;
    reg        branch_taken;
    reg [31:0] branch_target;

    wire [31:0] PC;
    wire [31:0] next_PC;
    wire [31:0] PC_plus_4;
    wire [31:0] instruction;
    wire [31:0] id_PC;
    wire [31:0] id_PC_plus_4;
    wire [31:0] id_instruction;
    
    Instruction_Fetch DUT1 (
        .clk          (clk),
        .rst          (rst),
        .stall        (stall),
        .branch_taken (branch_taken),
        .branch_target(branch_target),
        .PC           (PC),
        .next_PC      (next_PC),
        .PC_plus_4    (PC_plus_4),
        .instruction  (instruction)
    );

    IF_ID_Register DUT2 (
        .clk           (clk),
        .rst           (rst),
        .stall         (stall),
        .flush         (flush),
        .if_PC         (PC),
        .if_PC_plus_4   (PC_plus_4),
        .if_instruction(instruction),
        .id_PC         (id_PC),
        .id_PC_plus_4   (id_PC_plus_4),
        .id_instruction(id_instruction)
    );

    always #5 clk =~clk;
        
    initial begin
        $dumpfile("fetch_test.vcd");
        $dumpvars(0, tb_fetch);

        // Initialize signals
        clk           = 0;
        rst           = 1;
        stall         = 0;
        flush         = 0;
        branch_taken  = 0;
        branch_target = 32'd0;

        // Realease reset
        #20; rst = 0;
        #30;

        //stall
        stall = 1; #20;
        stall = 0; #10;

        // branch taken
        branch_target = 32'h0000_0008;
        branch_taken  = 1; #10;
        branch_taken  = 0; #10;

        //flush
        flush = 1; #10;
        flush = 0;
        #30;
        $finish;
    end

endmodule

stage1_fetch/fetch_test.vcd
$date
	Thu Sep 24 18:58:18 2026
$end
$version
	Icarus Verilog
$end
$timescale
	1ps
$end
$scope module tb_fetch $end
$var wire 32 ! next_PC [31:0] $end
$var wire 32 " instruction [31:0] $end
$var wire 32 # id_instruction [31:0] $end
$var wire 32 $ id_PC_plus_4 [31:0] $end
$var wire 32 % id_PC [31:0] $end
$var wire 32 & PC_plus_4 [31:0] $end
$var wire 32 ' PC [31:0] $end
$var reg 1 ( branch_taken $end
$var reg 32 ) branch_target [31:0] $end
$var reg 1 * clk $end
$var reg 1 + flush $end
$var reg 1 , rst $end
$var reg 1 - stall $end
$scope module DUT1 $end
$var wire 1 ( branch_taken $end
$var wire 32 . branch_target [31:0] $end
$var wire 1 * clk $end
$var wire 32 / instruction [31:0] $end
$var wire 1 , rst $end
$var wire 1 - stall $end
$var wire 32 0 next_PC [31:0] $end
$var wire 32 1 PC_plus_4 [31:0] $end
$var reg 32 2 PC [31:0] $end
$upscope $end
$scope module DUT2 $end
$var wire 1 * clk $end
$var wire 1 + flush $end
$var wire 32 3 if_PC [31:0] $end
$var wire 32 4 if_PC_plus_4 [31:0] $end
$var wire 32 5 if_instruction [31:0] $end
$var wire 1 , rst $end
$var wire 1 - stall $end
$var reg 32 6 id_PC [31:0] $end
$var reg 32 7 id_PC_plus_4 [31:0] $end
$var reg 32 8 id_instruction [31:0] $end
$upscope $end
$upscope $end
$enddefinitions $end
#0
$dumpvars
bx 8
bx 7
bx 6
bx 5
bx 4
bx 3
bx 2
bx 1
bx 0
bx /
b0 .
0-
1,
0+
0*
b0 )
0(
bx '
bx &
bx %
bx $
bx #
bx "
bx !
$end
#5000
b100 !
b100 0
b10100000000000010010011 "
b10100000000000010010011 /
b10100000000000010010011 5
b100 &
b100 1
b100 4
b0 '
b0 2
b0 3
b0 $
b0 7
b0 %
b0 6
b10011 #
b10011 8
1*
#10000
0*
#15000
1*
#20000
0*
0,
#25000
b1000 !
b1000 0
b101000000000000100010011 "
b101000000000000100010011 /
b101000000000000100010011 5
b1000 &
b1000 1
b1000 4
b100 '
b100 2
b100 3
b100 $
b100 7
b10100000000000010010011 #
b10100000000000010010011 8
1*
#30000
0*
#35000
b1100 !
b1100 0
b1000001000000110110011 "
b1000001000000110110011 /
b1000001000000110110011 5
b1000 $
b1000 7
b100 %
b100 6
b101000000000000100010011 #
b101000000000000100010011 8
b1100 &
b1100 1
b1100 4
b1000 '
b1000 2
b1000 3
1*
#40000
0*
#45000
b10000 !
b10000 0
b1000000001000001000001000110011 "
b1000000001000001000001000110011 /
b1000000001000001000001000110011 5
b10000 &
b10000 1
b10000 4
b1100 '
b1100 2
b1100 3
b1100 $
b1100 7
b1000 %
b1000 6
b1000001000000110110011 #
b1000001000000110110011 8
1*
#50000
0*
1-
#55000
1*
#60000
0*
#65000
1*
#70000
0*
0-
#75000
b10100 !
b10100 0
b1100010000001010110011 "
b1100010000001010110011 /
b1100010000001010110011 5
b10000 $
b10000 7
b1100 %
b1100 6
b1000000001000001000001000110011 #
b1000000001000001000001000110011 8
b10100 &
b10100 1
b10100 4
b10000 '
b10000 2
b10000 3
1*
#80000
b1000 !
b1000 0
0*
1(
b1000 )
b1000 .
#85000
b1000001000000110110011 "
b1000001000000110110011 /
b1000001000000110110011 5
b1100 &
b1100 1
b1100 4
b1000 '
b1000 2
b1000 3
b10100 $
b10100 7
b10000 %
b10000 6
b1100010000001010110011 #
b1100010000001010110011 8
1*
#90000
b1100 !
b1100 0
0*
0(
#95000
b10000 !
b10000 0
b1000000001000001000001000110011 "
b1000000001000001000001000110011 /
b1000000001000001000001000110011 5
b1100 $
b1100 7
b1000 %
b1000 6
b1000001000000110110011 #
b1000001000000110110011 8
b10000 &
b10000 1
b10000 4
b1100 '
b1100 2
b1100 3
1*
#100000
0*
1+
#105000
b10100 !
b10100 0
b1100010000001010110011 "
b1100010000001010110011 /
b1100010000001010110011 5
b10100 &
b10100 1
b10100 4
b10000 '
b10000 2
b10000 3
b0 $
b0 7
b0 %
b0 6
b10011 #
b10011 8
1*
#110000
0*
0+
#115000
b11000 !
b11000 0
b10011 "
b10011 /
b10011 5
b10100 $
b10100 7
b10000 %
b10000 6
b1100010000001010110011 #
b1100010000001010110011 8
b11000 &
b11000 1
b11000 4
b10100 '
b10100 2
b10100 3
1*
#120000
0*
#125000
b11100 !
b11100 0
bx "
bx /
bx 5
b11100 &
b11100 1
b11100 4
b11000 '
b11000 2
b11000 3
b11000 $
b11000 7
b10100 %
b10100 6
b10011 #
b10011 8
1*
#130000
0*
#135000
b100000 !
b100000 0
b11100 $
b11100 7
b11000 %
b11000 6
bx #
bx 8
b100000 &
b100000 1
b100000 4
b11100 '
b11100 2
b11100 3
1*
